CHANGES.txt
README.txt
bootstrap.py
buildout.cfg
setup.py
src/zope/__init__.py
src/zope.app.boston.egg-info/PKG-INFO
src/zope.app.boston.egg-info/SOURCES.txt
src/zope.app.boston.egg-info/dependency_links.txt
src/zope.app.boston.egg-info/namespace_packages.txt
src/zope.app.boston.egg-info/not-zip-safe
src/zope.app.boston.egg-info/requires.txt
src/zope.app.boston.egg-info/top_level.txt
src/zope/app/__init__.py
src/zope/app/boston/README.txt
src/zope/app/boston/SETUP.cfg
src/zope/app/boston/__init__.py
src/zope/app/boston/boston_description.png
src/zope/app/boston/boston_layout.png
src/zope/app/boston/boston_layout_v2.png
src/zope/app/boston/configure.zcml
src/zope/app/boston/ftesting.zcml
src/zope/app/boston/testing.py
src/zope/app/boston/tests.py
src/zope/app/boston/zope.app.boston-configure.zcml
src/zope/app/boston/browser/__init__.py
src/zope/app/boston/browser/boston.js
src/zope/app/boston/browser/configure.zcml
src/zope/app/boston/browser/skin.css
src/zope/app/boston/browser/standardmacros.py
src/zope/app/boston/browser/template.pt
src/zope/app/boston/browser/tests.py
src/zope/app/boston/browser/widget.css
src/zope/app/boston/browser/widget_macros.pt
src/zope/app/boston/browser/img/favicon.png
src/zope/app/boston/browser/img/zopelogo.gif
src/zope/app/boston/viewlets/__init__.py
src/zope/app/boston/viewlets/configure.zcml
src/zope/app/boston/viewlets/addinginfo/__init__.py
src/zope/app/boston/viewlets/addinginfo/browser.py
src/zope/app/boston/viewlets/addinginfo/configure.zcml
src/zope/app/boston/viewlets/addinginfo/interfaces.py
src/zope/app/boston/viewlets/addinginfo/viewlet.pt
src/zope/app/boston/viewlets/toolbar/__init__.py
src/zope/app/boston/viewlets/toolbar/browser.py
src/zope/app/boston/viewlets/toolbar/configure.zcml
src/zope/app/boston/viewlets/toolbar/interfaces.py
src/zope/app/boston/viewlets/toolbar/macros.pt
src/zope/app/boston/viewlets/toolbar/toolbar.css
src/zope/app/boston/viewlets/toolbar/toolbarGrip.gif
src/zope/app/boston/viewlets/toolbar/viewlet.pt
src/zope/app/boston/viewlets/xmltree/__init__.py
src/zope/app/boston/viewlets/xmltree/configure.zcml
src/zope/app/boston/viewlets/xmltree/xmltree.css
src/zope/app/boston/viewlets/xmltree/xmltree.pt